LICENSE
callable_journal/__init__.py
callable_journal/encoders.py
callable_journal/exception_msg.py
callable_journal/exceptions.py
callable_journal/formatter.py
callable_journal/journal.py
callable_journal/param_arg_mapper.py
callable_journal-0.0.9.dist-info/LICENSE
callable_journal-0.0.9.dist-info/WHEEL
callable_journal-0.0.9.dist-info/METADATA
callable_journal-0.0.9.dist-info/RECORD
