Metadata-Version: 2.1
Name: callable-journal
Version: 0.0.9
Summary: Log message generator for a callable's argument and return values.
Home-page: https://github.com/nathan5280/ndl-tools
License: MIT
Keywords: api,testing,diff
Author: Nate Atkins
Author-email: atkinsnw@gmail.com
Requires-Python: >=3.7,<4.0
Classifier: License :: OSI Approved :: MIT License
Classifier: Operating System :: OS Independent
Classifier: Programming Language :: Python :: 3
Classifier: Programming Language :: Python :: 3.7
Classifier: Programming Language :: Python :: 3.8
Classifier: Topic :: System :: Logging
Requires-Dist: ndl-tools (>=0.0.18,<0.0.19)
Requires-Dist: pydantic (>=1.6.1,<2.0.0)
Requires-Dist: pyyaml (>=5.3.1,<6.0.0)
Requires-Dist: toolz (>=0.10.0,<0.11.0)
Project-URL: Repository, https://github.com/nathan5280/ndl-tools
